celldetective/__init__.py
celldetective/__main__.py
celldetective/_version.py
celldetective/events.py
celldetective/exceptions.py
celldetective/extra_properties.py
celldetective/filters.py
celldetective/io.py
celldetective/measure.py
celldetective/neighborhood.py
celldetective/preprocessing.py
celldetective/relative_measurements.py
celldetective/segmentation.py
celldetective/signals.py
celldetective/tracking.py
celldetective/utils.py
celldetective/datasets/segmentation_annotations/blank
celldetective/datasets/signal_annotations/blank
celldetective/gui/InitWindow.py
celldetective/gui/__init__.py
celldetective/gui/about.py
celldetective/gui/analyze_block.py
celldetective/gui/base_annotator.py
celldetective/gui/base_components.py
celldetective/gui/classifier_widget.py
celldetective/gui/configure_new_exp.py
celldetective/gui/control_panel.py
celldetective/gui/event_annotator.py
celldetective/gui/generic_signal_plot.py
celldetective/gui/gui_utils.py
celldetective/gui/json_readers.py
celldetective/gui/layouts.py
celldetective/gui/pair_event_annotator.py
celldetective/gui/plot_measurements.py
celldetective/gui/plot_signals_ui.py
celldetective/gui/process_block.py
celldetective/gui/seg_model_loader.py
celldetective/gui/styles.py
celldetective/gui/survival_ui.py
celldetective/gui/tableUI.py
celldetective/gui/thresholds_gui.py
celldetective/gui/viewers.py
celldetective/gui/workers.py
celldetective/gui/help/DL-segmentation-strategy.json
celldetective/gui/help/Threshold-vs-DL.json
celldetective/gui/help/cell-populations.json
celldetective/gui/help/exp-structure.json
celldetective/gui/help/feature-btrack.json
celldetective/gui/help/neighborhood.json
celldetective/gui/help/prefilter-for-segmentation.json
celldetective/gui/help/preprocessing.json
celldetective/gui/help/propagate-classification.json
celldetective/gui/help/track-postprocessing.json
celldetective/gui/help/tracking.json
celldetective/gui/processes/compute_neighborhood.py
celldetective/gui/processes/downloader.py
celldetective-1.4.1.dist-info/licenses/LICENSE
celldetective-1.4.1.dist-info/METADATA
celldetective-1.4.1.dist-info/WHEEL
celldetective-1.4.1.dist-info/entry_points.txt
celldetective-1.4.1.dist-info/top_level.txt
celldetective-1.4.1.dist-info/RECORD
