Metadata-Version: 2.4
Name: celldetective
Version: 1.4.1
Summary: description
Home-page: http://github.com/remyeltorro/celldetective
Author: Rémy Torro
Author-email: remy.torro@inserm.fr
License: GPL-3.0
License-File: LICENSE
Requires-Dist: wheel
Requires-Dist: nbsphinx
Requires-Dist: nbsphinx_link
Requires-Dist: sphinx_rtd_theme
Requires-Dist: sphinx
Requires-Dist: jinja2
Requires-Dist: ipykernel
Requires-Dist: stardist
Requires-Dist: cellpose<3
Requires-Dist: scikit-learn
Requires-Dist: btrack
Requires-Dist: tensorflow~=2.15.0
Requires-Dist: napari<0.6.0
Requires-Dist: tqdm
Requires-Dist: mahotas
Requires-Dist: fonticon-materialdesignicons6
Requires-Dist: art
Requires-Dist: lifelines
Requires-Dist: setuptools
Requires-Dist: scipy
Requires-Dist: seaborn
Requires-Dist: opencv-python-headless==4.7.0.72
Requires-Dist: PyQt5
Requires-Dist: liblapack
Requires-Dist: gputools
Requires-Dist: lmfit
Requires-Dist: superqt[cmap]
Requires-Dist: setuptools
Requires-Dist: matplotlib_scalebar
Requires-Dist: numpy==1.26.4
Requires-Dist: pytest
Requires-Dist: pytest-qt
Requires-Dist: h5py
Requires-Dist: cliffs_delta
Requires-Dist: requests
Requires-Dist: trackpy
Requires-Dist: prettyprint
Requires-Dist: pandas
Requires-Dist: matplotlib
Requires-Dist: prettytable
Dynamic: author
Dynamic: author-email
Dynamic: description
Dynamic: description-content-type
Dynamic: home-page
Dynamic: license
Dynamic: license-file
Dynamic: requires-dist
Dynamic: summary
